README.rst
ptt.py
setup.py
ptt.py.egg-info/PKG-INFO
ptt.py.egg-info/SOURCES.txt
ptt.py.egg-info/dependency_links.txt
ptt.py.egg-info/entry_points.txt
ptt.py.egg-info/requires.txt
ptt.py.egg-info/top_level.txt